[
  {
    "file_name": "4.jpeg",
    "size": "w"
  },
  {
    "file_name": "2.jpeg",
    "size": "z"
  },
  {
    "file_name": "24.jpeg/Sat Mar 30 21:57:05 2013",
    "size": "w"
  },
  {
    "file_name": "24.jpeg/Wed May  1 17:18:27 2013",
    "size": "w"
  },
  {
    "file_name": "18.jpeg",
    "size": "w"
  },
  {
    "file_name": "1.jpeg",
    "size": "w"
  },
  {
    "file_name": "13.jpeg",
    "size": "w"
  },
  {
    "file_name": "38.jpeg",
    "size": "w"
  },
  {
    "file_name": "24.jpeg/Tue Apr 28 18:08:03 2015",
    "size": "z"
  },
  {
    "file_name": "6.jpeg",
    "size": "z"
  },
  {
    "file_name": "12.jpeg",
    "size": "x"
  },
  {
    "file_name": "30.jpeg",
    "size": "w"
  },
  {
    "file_name": "26.jpeg",
    "size": "w"
  },
  {
    "file_name": "46.jpeg",
    "size": "z"
  },
  {
    "file_name": "17.jpeg/Thu Sep 14 21:20:53 2017",
    "size": "w"
  },
  {
    "file_name": "7.jpeg",
    "size": "z"
  },
  {
    "file_name": "17.jpeg/Fri Oct 25 13:11:39 2019",
    "size": "w"
  }
]